wicope/__init__.py
wicope/__main__.py
wicope/app.py
wicope/controller.py
wicope/device.py
wicope/main_window.py
wicope-0.1.0b1.dist-info/METADATA
wicope-0.1.0b1.dist-info/WHEEL
wicope-0.1.0b1.dist-info/entry_points.txt
wicope-0.1.0b1.dist-info/top_level.txt
wicope-0.1.0b1.dist-info/RECORD
